ariadne/__init__.py
ariadne/__version__.py
ariadne/classifier.py
ariadne/protocol.py
ariadne/server.py
ariadne/util.py
ariadne/contrib/__init__.py
ariadne/contrib/inception_util.py
ariadne/contrib/the_classifier.py
scripts/__init__.py
scripts/convert_imdb_reviews.py
scripts/convert_sentiment_labelled_sentences.py
scripts/tester.py
scripts/util.py
inception_rec-0.1.0.dist-info/LICENSE.txt
inception_rec-0.1.0.dist-info/METADATA
inception_rec-0.1.0.dist-info/WHEEL
inception_rec-0.1.0.dist-info/top_level.txt
inception_rec-0.1.0.dist-info/RECORD
