Metadata-Version: 2.1
Name: inception-rec
Version: 0.1.0
Summary: INCEpTION external recommender library in Python
Home-page: https://inception-project.github.io/
Author: The INCEpTION team
Author-email: inception-users@googlegroups.com
License: Apache License 2.0
Project-URL: Bug Tracker, https://github.com/serge-sotnyk/inception-external-recommender/issues
Project-URL: Documentation, https://github.com/inception-project/inception-external-recommender
Project-URL: Source Code, https://github.com/serge-sotnyk/inception-external-recommender
Keywords: uima dkpro inception nlp
Platform: UNKNOWN
Classifier: Development Status :: 4 - Beta
Classifier: Intended Audience :: Developers
Classifier: Intended Audience :: Science/Research
Classifier: License :: OSI Approved :: Apache Software License
Classifier: Programming Language :: Python :: 3 :: Only
Classifier: Programming Language :: Python :: 3.5
Classifier: Programming Language :: Python :: 3.6
Classifier: Programming Language :: Python :: 3.7
Classifier: Topic :: Software Development :: Libraries
Classifier: Topic :: Scientific/Engineering :: Human Machine Interfaces
Classifier: Topic :: Text Processing :: Linguistic
Requires-Python: >=3.6.0
Provides-Extra: test
Provides-Extra: dev
Provides-Extra: doc
Provides-Extra: contrib
License-File: LICENSE.txt
